Metadata-Version: 2.1
Name: dash-interactive-graphviz
Version: 0.1.1
Summary: An interactive graphviz viewer for Dash
Home-page: UNKNOWN
Author: James Saunders <james@businessoptics.biz>
License: MIT
Platform: UNKNOWN
Classifier: Framework :: Dash
